minke/__init__.py
minke/__main__.py
minke/asimov.py
minke/bilby.py
minke/cli.py
minke/detector.py
minke/distribution.py
minke/filters.py
minke/injection.py
minke/mdctools.py
minke/minke_template.yml
minke/noise.py
minke/sources.py
minke/types.py
minke/utils.py
minke/models/__init__.py
minke/models/bursts.py
minke/models/cbc.py
minke/models/lalburst.py
minke/models/lalnoise.py
minke/models/lalsimulation.py
minke-2.1.2.dist-info/licenses/AUTHORS.rst
minke-2.1.2.dist-info/licenses/LICENSE
minke-2.1.2.dist-info/METADATA
minke-2.1.2.dist-info/WHEEL
minke-2.1.2.dist-info/entry_points.txt
minke-2.1.2.dist-info/top_level.txt
minke-2.1.2.dist-info/RECORD
