Metadata-Version: 2.4
Name: minke
Version: 2.1.2
Summary: A package to make generating gravitational waveforms easier.
Author-email: Daniel Williams <daniel.williams@ligo.org>
License: MIT
Project-URL: Source code, https://git.ligo.org/daniel-williams/minke
Classifier: Programming Language :: Python :: 3
Classifier: License :: OSI Approved :: MIT License
Classifier: Operating System :: OS Independent
Requires-Python: >=3.7
License-File: LICENSE
License-File: AUTHORS.rst
Requires-Dist: asimov>=0.5.0
Requires-Dist: otter-report
Requires-Dist: pandas
Requires-Dist: lalsuite
Requires-Dist: ligotimegps
Requires-Dist: igwn-ligolw
Requires-Dist: gwpy
Provides-Extra: docs
Requires-Dist: sphinx; extra == "docs"
Requires-Dist: kentigern; extra == "docs"
Dynamic: license-file
